crayon/__init__.py
crayon/cli.py
crayon/resources.py
crayon/training.py
crayon/adaptive/__init__.py
crayon/adaptive/manager.py
crayon/adaptive/stability.py
crayon/adaptive/updater.py
crayon/c_ext/__init__.py
crayon/c_ext/cpu_engine.cpp
crayon/c_ext/crayon_cpu.cp313-win_amd64.pyd
crayon/c_ext/crayon_module.c
crayon/c_ext/dat_builder.py
crayon/c_ext/gpu_engine_cuda.cu
crayon/c_ext/rocm_engine.cpp
crayon/c_ext/simd_ops.c
crayon/c_ext/simd_ops.h
crayon/c_ext/trie_node.h
crayon/concurrency/__init__.py
crayon/concurrency/pipeline.py
crayon/concurrency/thread_local.py
crayon/core/__init__.py
crayon/core/dat_compiler.py
crayon/core/primitives.py
crayon/core/profiles.py
crayon/core/tokenizer.py
crayon/core/vocab_builder.py
crayon/core/vocabulary.py
crayon/memory/__init__.py
crayon/memory/cache.py
crayon/memory/pool.py
crayon/memory/zerocopy.py
crayon/resources/__init__.py
crayon/resources/arts_commerce_corpus.txt
crayon/resources/code_corpus.txt
crayon/resources/data.csv
crayon/resources/graduate_math.txt
crayon/resources/input.txt
crayon/resources/multilingual_corpus.txt
crayon/resources/physics_detailed_dataset_700_rows.csv
crayon/resources/science_corpus.txt
crayon/resources/dat/__init__.py
crayon/resources/dat/vocab_arts_commerce.dat
crayon/resources/dat/vocab_arts_commerce.json
crayon/resources/dat/vocab_code.dat
crayon/resources/dat/vocab_code.json
crayon/resources/dat/vocab_lite.dat
crayon/resources/dat/vocab_lite.json
crayon/resources/dat/vocab_multilingual.dat
crayon/resources/dat/vocab_multilingual.json
crayon/resources/dat/vocab_science.dat
crayon/resources/dat/vocab_science.json
crayon/unicode/__init__.py
crayon/unicode/multilingual.py
crayon/unicode/normalizer.py
xerv_crayon-4.1.9.dist-info/licenses/LICENSE
xerv_crayon-4.1.9.dist-info/METADATA
xerv_crayon-4.1.9.dist-info/WHEEL
xerv_crayon-4.1.9.dist-info/entry_points.txt
xerv_crayon-4.1.9.dist-info/top_level.txt
xerv_crayon-4.1.9.dist-info/RECORD
