Metadata-Version: 2.4
Name: xerv-crayon
Version: 4.1.9
Summary: Omni-Backend Tokenizer - CPU (AVX2/512), CUDA (NVIDIA), ROCm (AMD) with automatic hardware detection
Author-email: Xerv Research Engineering Division <engineering@xerv.ai>
License: MIT License
Project-URL: Homepage, https://github.com/xerv/crayon
Project-URL: Repository, https://github.com/xerv/crayon.git
Project-URL: Documentation, https://github.com/xerv/crayon#readme
Project-URL: Bug Tracker, https://github.com/xerv/crayon/issues
Keywords: tokenizer,nlp,simd,avx2,avx512,cuda,rocm,gpu,high-performance,zero-copy,dat,double-array-trie,machine-learning,deep-learning,transformers,llm,nvcuda,amd,nvidia
Classifier: Development Status :: 5 - Production/Stable
Classifier: Intended Audience :: Science/Research
Classifier: Intended Audience :: Developers
Classifier: License :: OSI Approved :: MIT License
Classifier: Programming Language :: Python :: 3
Classifier: Programming Language :: Python :: 3.10
Classifier: Programming Language :: Python :: 3.11
Classifier: Programming Language :: Python :: 3.12
Classifier: Programming Language :: Python :: 3.13
Classifier: Programming Language :: C
Classifier: Programming Language :: C++
Classifier: Topic :: Scientific/Engineering :: Artificial Intelligence
Classifier: Topic :: Text Processing :: Linguistic
Classifier: Operating System :: POSIX :: Linux
Classifier: Operating System :: Microsoft :: Windows
Classifier: Operating System :: MacOS
Classifier: Environment :: GPU :: NVIDIA CUDA
Requires-Python: >=3.10
License-File: LICENSE
Provides-Extra: full
Requires-Dist: requests>=2.31.0; extra == "full"
Requires-Dist: datasets>=2.18.0; extra == "full"
Requires-Dist: huggingface-hub>=0.21.0; extra == "full"
Provides-Extra: dev
Requires-Dist: pytest>=7.0.0; extra == "dev"
Requires-Dist: pytest-benchmark>=4.0.0; extra == "dev"
Requires-Dist: build>=1.0.0; extra == "dev"
Requires-Dist: twine>=4.0.0; extra == "dev"
Provides-Extra: benchmark
Requires-Dist: tiktoken>=0.5.0; extra == "benchmark"
Requires-Dist: transformers>=4.30.0; extra == "benchmark"
Requires-Dist: matplotlib>=3.7.0; extra == "benchmark"
Dynamic: license-file
Dynamic: requires-python
